README.md
setup.py
fmutils/__init__.py
fmutils/directorytree.py
fmutils/fmutils.py
fmutils/plottingutils.py
fmutils.egg-info/PKG-INFO
fmutils.egg-info/SOURCES.txt
fmutils.egg-info/dependency_links.txt
fmutils.egg-info/requires.txt
fmutils.egg-info/top_level.txt