Metadata-Version: 2.1
Name: fmutils
Version: 0.2.0
Summary: Package for easily accessing and managing large number of files and dirs (e.g. in ML datasets).
Home-page: https://github.com/Mr-TalhaIlyas/FMUtils
Author: Talha Ilyas
Author-email: mr.talhailyas@gmail.com
License: UNKNOWN
Keywords: python,directory tree generator,files management,directory management,files listing,directories listing,deleting files,randomly selecting file,transformer,IQA
Platform: UNKNOWN
Classifier: Intended Audience :: Education
Classifier: Programming Language :: Python :: 3
Classifier: License :: OSI Approved :: MIT License
Classifier: Operating System :: OS Independent
